ytl_model/__init__.py
ytl_model/enums.py
ytl_model/models.py
ytl_model-1.5.0.dist-info/METADATA
ytl_model-1.5.0.dist-info/WHEEL
ytl_model-1.5.0.dist-info/RECORD
