Metadata-Version: 2.3
Name: ytl-model
Version: 1.5.0
Summary: Just some models and enums
Author-email: alexdelorenzo <3579286+alexdelorenzo@users.noreply.github.com>
Requires-Python: >=3.8
Requires-Dist: pydantic>=2.8.2
